nonechucks/__init__.py
nonechucks/dataloader.py
nonechucks/dataset.py
nonechucks/sampler.py
nonechucks/utils.py
nonechucks-0.4.2.dist-info/LICENSE
nonechucks-0.4.2.dist-info/METADATA
nonechucks-0.4.2.dist-info/WHEEL
nonechucks-0.4.2.dist-info/top_level.txt
nonechucks-0.4.2.dist-info/RECORD
