Metadata-Version: 2.1
Name: nonechucks
Version: 0.4.2
Summary: nonechucks is a library that provides wrappers for PyTorch's datasets, samplers, and transforms to allow for dropping unwanted or invalid samples dynamically.
Home-page: https://github.com/msamogh/nonechucks
Author: Amogh Mannekote
Author-email: msamogh@gmail.com
License: MIT
Platform: UNKNOWN
Requires-Dist: future
